simple_tsne/__init__.py
simple_tsne/main.py
simple_tsne-1.0.0.dist-info/METADATA
simple_tsne-1.0.0.dist-info/WHEEL
simple_tsne-1.0.0.dist-info/top_level.txt
simple_tsne-1.0.0.dist-info/RECORD
